django_cbim_general_service/__init__.py
django_cbim_general_service/apps.py
django_cbim_general_service/backends.py
django_cbim_general_service/cache.py
django_cbim_general_service/conf.py
django_cbim_general_service/middleware.py
django_cbim_general_service/models.py
django_cbim_general_service/tests.py
django_cbim_general_service/urls.py
django_cbim_general_service/validators.py
django_cbim_general_service/version.py
django_cbim_general_service/views.py
django_cbim_general_service/graphqls/__init__.py
django_cbim_general_service/graphqls/queries_and_mutations.py
django_cbim_general_service/graphqls/types.py
django_cbim_general_service/migrations/0000_initial.py
django_cbim_general_service/migrations/0001_create_group_permissions.py
django_cbim_general_service/migrations/0002_create_user_permissions.py
django_cbim_general_service/migrations/0003_remove_user_unused_tables_20210624_1712.py
django_cbim_general_service/migrations/__init__.py
django_cbim_general_service/settings/__init__.py
django_cbim_general_service/settings/cbim_settings_helper.py
django_cbim_general_service-1.13.10.dist-info/LICENSE.md
django_cbim_general_service-1.13.10.dist-info/METADATA
django_cbim_general_service-1.13.10.dist-info/WHEEL
django_cbim_general_service-1.13.10.dist-info/top_level.txt
django_cbim_general_service-1.13.10.dist-info/RECORD
